{
  "title": "6. CSI: Container Scene Investigation",
  "description": "Containers die. It's your job to find out why. Master the art of debugging with `logs`, `inspect`, and `exec`.",
  "details": {
    "intro": {
      "text": "intro.md",
      "background": "setup.sh"
    },
    "steps": [
      {
        "title": "The Silent Treatment (Logs)",
        "text": "step1/text.md",
        "verify": "step1/verify.sh"
      },
      {
        "title": "Breaking In (Exec & Inspect)",
        "text": "step2/text.md",
        "verify": "step2/verify.sh"
      },
      {
        "title": "Crash Course (CrashLoopBackOff)",
        "text": "step3/text.md",
        "verify": "step3/verify.sh"
      },
      {
        "title": "Port Conflict (Address In Use)",
        "text": "step4/text.md",
        "verify": "step4/verify.sh"
      }
    ],
    "finish": {
      "text": "finish.md"
    }
  },
  "backend": {
    "imageid": "ubuntu"
  }
}